{
  "id": 24735152712200,
  "events": {
    "09:50 Vaal": {
      "id": 1954117796390016,
      "start": "2022-01-06T09:50:00.000Z",
      "allRunners": {
        "1 Coming In Hot": {
          "runnerId": 1954117797400016,
          "back": 0,
          "lay": 0
        },
        "2 Abayyaan": {
          "runnerId": 1954117797440016,
          "back": 2.1,
          "lay": 4.7
        },
        "3 Captain Persia": {
          "runnerId": 1954117797470016,
          "back": 0,
          "lay": 0
        },
        "4 Back To Basics": {
          "runnerId": 1954117797500116,
          "back": 0,
          "lay": 0
        },
        "5 Black Burner": {
          "runnerId": 1954117797530116,
          "back": 0,
          "lay": 0
        },
        "6 Orgetorix": {
          "runnerId": 1954117797570016,
          "back": 0,
          "lay": 0
        },
        "7 Equerry": {
          "runnerId": 1954117797600016,
          "back": 0,
          "lay": 0
        },
        "8 Aspiringtoreign": {
          "runnerId": 1954117797640016,
          "back": 0,
          "lay": 0
        },
        "9 Final Declaration": {
          "runnerId": 1954117797670016,
          "back": 0,
          "lay": 0
        },
        "11 Mactavish": {
          "runnerId": 1954117797730016,
          "back": 3.5,
          "lay": 100
        },
        "12 Real Churchy": {
          "runnerId": 1954117797760016,
          "back": 3.5,
          "lay": 0
        },
        "13 Thornton Creek": {
          "runnerId": 1954117797790016,
          "back": 0,
          "lay": 0
        },
        "10 Knock Twice": {
          "runnerId": 1954117797700016,
          "back": 0,
          "lay": 0
        }
      }
    },
    "10:25 Vaal": {
      "id": 1954117798820016,
      "start": "2022-01-06T10:25:00.000Z",
      "allRunners": {
        "1 Bartholdi": {
          "runnerId": 1954117799370016,
          "back": 0,
          "lay": 0
        },
        "2 Invidia": {
          "runnerId": 1954117799400016,
          "back": 0,
          "lay": 0
        },
        "3 Captain Morisco": {
          "runnerId": 1954117799420116,
          "back": 0,
          "lay": 0
        },
        "4 Mufasa": {
          "runnerId": 1954117799450116,
          "back": 0,
          "lay": 0
        },
        "5 Gallic Chief": {
          "runnerId": 1954117799480116,
          "back": 0,
          "lay": 0
        },
        "6 Heavens Girl": {
          "runnerId": 1954117799510116,
          "back": 0,
          "lay": 0
        },
        "7 Volluto": {
          "runnerId": 1954117799540116,
          "back": 0,
          "lay": 0
        }
      }
    },
    "11:00 Vaal": {
      "id": 1954117799910016,
      "start": "2022-01-06T11:00:00.000Z",
      "allRunners": {
        "1 Sky Glitter": {
          "runnerId": 1954117800830016,
          "back": 0,
          "lay": 0
        },
        "2 Namibsroos": {
          "runnerId": 1954117800870016,
          "back": 0,
          "lay": 0
        },
        "3 Lil Wahoo": {
          "runnerId": 1954117800900116,
          "back": 0,
          "lay": 0
        },
        "4 Covermeinsunshine": {
          "runnerId": 1954117800930116,
          "back": 0,
          "lay": 0
        },
        "5 Petunia": {
          "runnerId": 1954117800970016,
          "back": 0,
          "lay": 0
        },
        "6 Nommo": {
          "runnerId": 1954117801000016,
          "back": 0,
          "lay": 0
        },
        "7 Angel's Wish": {
          "runnerId": 1954117801030016,
          "back": 0,
          "lay": 0
        },
        "8 Blue Meteor": {
          "runnerId": 1954117801060116,
          "back": 0,
          "lay": 0
        },
        "9 In The Ether": {
          "runnerId": 1954117801090116,
          "back": 0,
          "lay": 0
        },
        "10 Raising A Storm": {
          "runnerId": 1954117801120116,
          "back": 0,
          "lay": 0
        },
        "12 Super Hot": {
          "runnerId": 1954117801190016,
          "back": 0,
          "lay": 0
        },
        "13 Yours Truly": {
          "runnerId": 1954117801220116,
          "back": 0,
          "lay": 0
        },
        "11 Spanish Spirit": {
          "runnerId": 1954117801160016,
          "back": 0,
          "lay": 0
        }
      }
    },
    "11:35 Vaal": {
      "id": 1954117801810016,
      "start": "2022-01-06T11:35:00.000Z",
      "allRunners": {
        "1 Kissed By Fire": {
          "runnerId": 1954117802640016,
          "back": 0,
          "lay": 0
        },
        "2 Evoke": {
          "runnerId": 1954117802670016,
          "back": 0,
          "lay": 0
        },
        "3 Night Lily": {
          "runnerId": 1954117802700016,
          "back": 0,
          "lay": 0
        },
        "5 Maria's World": {
          "runnerId": 1954117802760016,
          "back": 0,
          "lay": 0
        },
        "6 Crown Plaza": {
          "runnerId": 1954117802790016,
          "back": 0,
          "lay": 0
        },
        "7 I Am Royal": {
          "runnerId": 1954117802820016,
          "back": 0,
          "lay": 0
        },
        "9 Elusive Rocket": {
          "runnerId": 1954117802890016,
          "back": 0,
          "lay": 0
        },
        "10 Jane Wilson": {
          "runnerId": 1954117802920016,
          "back": 0,
          "lay": 0
        },
        "11 Gift Of Giving": {
          "runnerId": 1954117802950016,
          "back": 0,
          "lay": 0
        },
        "12 Mon Tresor": {
          "runnerId": 1954117802980116,
          "back": 0,
          "lay": 0
        },
        "4 Quest From Afar": {
          "runnerId": 1954117802730016,
          "back": 0,
          "lay": 0
        },
        "8 Ankole": {
          "runnerId": 1954117802860016,
          "back": 0,
          "lay": 0
        }
      }
    },
    "12:05 Chepstow": {
      "id": 1953363315080016,
      "start": "2022-01-06T12:05:00.000Z",
      "allRunners": {
        "3 Lady Tremaine": {
          "runnerId": 1953363315910116,
          "back": 3.2,
          "lay": 5.5
        },
        "1 Dame du Soir": {
          "runnerId": 1953363315840016,
          "back": 5.5,
          "lay": 5.7
        },
        "4 Ruby Yeats": {
          "runnerId": 1953363315950016,
          "back": 7,
          "lay": 8.4
        },
        "9 Astra Via": {
          "runnerId": 1953363316110016,
          "back": 8.6,
          "lay": 20
        },
        "5 Lettie Lutz": {
          "runnerId": 1953363315980016,
          "back": 9,
          "lay": 13
        },
        "2 Heure De Gloire": {
          "runnerId": 1953363315880016,
          "back": 11.5,
          "lay": 24
        },
        "6 Llantara": {
          "runnerId": 1953363316010116,
          "back": 12.5,
          "lay": 21
        },
        "7 Jaunty Freyja": {
          "runnerId": 1953363316050016,
          "back": 13.5,
          "lay": 34
        },
        "8 Sarceaux": {
          "runnerId": 1953363316080016,
          "back": 12.5,
          "lay": 50
        }
      }
    },
    "12:10 Vaal": {
      "id": 1954117803480016,
      "start": "2022-01-06T12:10:00.000Z",
      "allRunners": {
        "1 Duke Of Rain": {
          "runnerId": 1954117804640016,
          "back": 0,
          "lay": 0
        },
        "2 Gimme A Dream": {
          "runnerId": 1954117804680016,
          "back": 0,
          "lay": 0
        },
        "4 Gold Ambition": {
          "runnerId": 1954117804740016,
          "back": 0,
          "lay": 0
        },
        "6 Takagari": {
          "runnerId": 1954117804810016,
          "back": 0,
          "lay": 0
        },
        "8 Admirals Moon": {
          "runnerId": 1954117804870116,
          "back": 0,
          "lay": 0
        },
        "9 Jaipur Jewel": {
          "runnerId": 1954117804900116,
          "back": 0,
          "lay": 0
        },
        "10 Kay Francis": {
          "runnerId": 1954117804930116,
          "back": 0,
          "lay": 0
        },
        "11 Ginjamatinja": {
          "runnerId": 1954117804970016,
          "back": 0,
          "lay": 0
        },
        "12 Royal Siege": {
          "runnerId": 1954117805000016,
          "back": 0,
          "lay": 0
        },
        "13 Rattle Bag": {
          "runnerId": 1954117805030016,
          "back": 0,
          "lay": 0
        },
        "14 Great Melody": {
          "runnerId": 1954117805060116,
          "back": 0,
          "lay": 0
        },
        "15 Masuulka": {
          "runnerId": 1954117805100016,
          "back": 0,
          "lay": 0
        },
        "16 The Great Romantic": {
          "runnerId": 1954117805130016,
          "back": 0,
          "lay": 0
        },
        "17 The Punisher": {
          "runnerId": 1954117805160016,
          "back": 0,
          "lay": 0
        },
        "3 Royal Tiger": {
          "runnerId": 1954117804710116,
          "back": 0,
          "lay": 0
        },
        "5 Mike The Pilot": {
          "runnerId": 1954117804770116,
          "back": 0,
          "lay": 0
        },
        "7 Absolute Value": {
          "runnerId": 1954117804840116,
          "back": 0,
          "lay": 0
        }
      }
    },
    "12:20 Clonmel": {
      "id": 1953359189600016,
      "start": "2022-01-06T12:20:00.000Z",
      "allRunners": {
        "6 Dinoblue": {
          "runnerId": 1953359190920016,
          "back": 3.55,
          "lay": 6.2
        },
        "2 Happy D'ex": {
          "runnerId": 1953359190790116,
          "back": 5,
          "lay": 18.5
        },
        "10 Mi Lighthouse": {
          "runnerId": 1953359191040016,
          "back": 7.6,
          "lay": 34
        },
        "13 Happywifehappylife": {
          "runnerId": 1953359191130016,
          "back": 10,
          "lay": 30
        },
        "1 Feddans": {
          "runnerId": 1953359190760016,
          "back": 12.5,
          "lay": 0
        },
        "3 Comedy Of Ice": {
          "runnerId": 1953359190820116,
          "back": 7,
          "lay": 0
        },
        "4 Coolroe Lady": {
          "runnerId": 1953359190860016,
          "back": 4.2,
          "lay": 0
        },
        "5 Courtbrack Lady": {
          "runnerId": 1953359190890016,
          "back": 7,
          "lay": 0
        },
        "7 Glenbeg Express": {
          "runnerId": 1953359190950016,
          "back": 6,
          "lay": 0
        },
        "8 Kentucky Dreamin": {
          "runnerId": 1953359190980016,
          "back": 7,
          "lay": 0
        },
        "9 La Prima Donna": {
          "runnerId": 1953359191010016,
          "back": 2.78,
          "lay": 0
        },
        "11 Must Be Dreaming": {
          "runnerId": 1953359191070016,
          "back": 3,
          "lay": 0
        },
        "12 Ellie Tom": {
          "runnerId": 1953359191100016,
          "back": 7,
          "lay": 0
        }
      }
    },
    "12:30 Newcastle": {
      "id": 1953362708710016,
      "start": "2022-01-06T12:30:00.000Z",
      "allRunners": {
        "2 International Law": {
          "runnerId": 1953362709570016,
          "back": 4.6,
          "lay": 6.8
        },
        "1 Kingson": {
          "runnerId": 1953362709540016,
          "back": 4.1,
          "lay": 5.9
        },
        "9 Rose Of Lancashire": {
          "runnerId": 1953362709790116,
          "back": 6.2,
          "lay": 7.8
        },
        "6 Iron Sheriff": {
          "runnerId": 1953362709690116,
          "back": 7,
          "lay": 13.5
        },
        "4 Vintage Polly": {
          "runnerId": 1953362709630016,
          "back": 8.8,
          "lay": 0
        },
        "8 Zealous": {
          "runnerId": 1953362709760016,
          "back": 9.4,
          "lay": 18
        },
        "5 Uccello": {
          "runnerId": 1953362709660016,
          "back": 11.5,
          "lay": 0
        },
        "7 Lofty": {
          "runnerId": 1953362709730016,
          "back": 10,
          "lay": 0
        },
        "3 So Macho": {
          "runnerId": 1953362709600016,
          "back": 12.5,
          "lay": 0
        },
        "10 Lukoutoldmakezebak": {
          "runnerId": 1953362709820116,
          "back": 21,
          "lay": 200
        },
        "11 Gloryella": {
          "runnerId": 1953362709850116,
          "back": 21,
          "lay": 0
        }
      }
    },
    "12:40 Chepstow": {
      "id": 1953363316930016,
      "start": "2022-01-06T12:40:00.000Z",
      "allRunners": {
        "7 Marco Island": {
          "runnerId": 1953363317960016,
          "back": 3.95,
          "lay": 5.5
        },
        "10 Port Or Starboard": {
          "runnerId": 1953363318060016,
          "back": 3.9,
          "lay": 5
        },
        "4 Git Maker": {
          "runnerId": 1953363317860016,
          "back": 4.8,
          "lay": 6.6
        },
        "3 Extraordinary Man": {
          "runnerId": 1953363317830016,
          "back": 5.5,
          "lay": 14
        },
        "8 Pachacuti": {
          "runnerId": 1953363317990116,
          "back": 8.8,
          "lay": 34
        },
        "2 Braganza Bay": {
          "runnerId": 1953363317790116,
          "back": 11,
          "lay": 17
        },
        "9 Pilgrims King": {
          "runnerId": 1953363318030016,
          "back": 15,
          "lay": 900
        },
        "1 Bert Wilson": {
          "runnerId": 1953363317760016,
          "back": 20,
          "lay": 0
        },
        "5 Hit The Silk": {
          "runnerId": 1953363317890016,
          "back": 34,
          "lay": 0
        },
        "6 Keplerian": {
          "runnerId": 1953363317930016,
          "back": 18.5,
          "lay": 0
        },
        "11 Stumps Or Slips": {
          "runnerId": 1953363318090116,
          "back": 0,
          "lay": 0
        },
        "12 Annie Nail": {
          "runnerId": 1953363318130016,
          "back": 10,
          "lay": 0
        }
      }
    },
    "12:45 Vaal": {
      "id": 1954117805860016,
      "start": "2022-01-06T12:45:00.000Z",
      "allRunners": {
        "1 Elusive Current": {
          "runnerId": 1954117806850016,
          "back": 0,
          "lay": 0
        },
        "2 Fantastical": {
          "runnerId": 1954117806880016,
          "back": 0,
          "lay": 0
        },
        "4 Rock Of Africa": {
          "runnerId": 1954117806940016,
          "back": 0,
          "lay": 0
        },
        "5 Nordic Rebel": {
          "runnerId": 1954117806970016,
          "back": 0,
          "lay": 0
        },
        "6 Suited Connector": {
          "runnerId": 1954117807000016,
          "back": 0,
          "lay": 0
        },
        "7 Battleoftrafalgar": {
          "runnerId": 1954117807030016,
          "back": 0,
          "lay": 0
        },
        "8 King's Crusade": {
          "runnerId": 1954117807060016,
          "back": 0,
          "lay": 0
        },
        "9 Bey Suyay": {
          "runnerId": 1954117807090016,
          "back": 0,
          "lay": 0
        },
        "10 Waqaas": {
          "runnerId": 1954117807120016,
          "back": 0,
          "lay": 0
        },
        "11 Snorting Bull": {
          "runnerId": 1954117807150016,
          "back": 0,
          "lay": 0
        },
        "12 Duke Of Sussex": {
          "runnerId": 1954117807180016,
          "back": 0,
          "lay": 0
        },
        "13 Power Ranger": {
          "runnerId": 1954117807210016,
          "back": 0,
          "lay": 0
        },
        "14 Hidden Agenda": {
          "runnerId": 1954117807230116,
          "back": 0,
          "lay": 0
        },
        "3 Ballon D'or": {
          "runnerId": 1954117806900116,
          "back": 0,
          "lay": 0
        }
      }
    },
    "12:50 Clonmel": {
      "id": 1953359193390016,
      "start": "2022-01-06T12:50:00.000Z",
      "allRunners": {
        "7 Gorki D'airy": {
          "runnerId": 1953359195150116,
          "back": 2,
          "lay": 3.05
        },
        "12 Mahons Glory": {
          "runnerId": 1953359195290116,
          "back": 2.76,
          "lay": 7.2
        },
        "11 Lieutenant Highway": {
          "runnerId": 1953359195270016,
          "back": 8,
          "lay": 0
        },
        "1 Ask The Bookie": {
          "runnerId": 1953359194990016,
          "back": 0,
          "lay": 0
        },
        "2 Carbon King": {
          "runnerId": 1953359195020016,
          "back": 4,
          "lay": 0
        },
        "3 Chapel Street": {
          "runnerId": 1953359195040116,
          "back": 4.2,
          "lay": 0
        },
        "4 Dont Doubt Me": {
          "runnerId": 1953359195070116,
          "back": 7,
          "lay": 0
        },
        "5 First Earl": {
          "runnerId": 1953359195100016,
          "back": 13,
          "lay": 0
        },
        "6 Golden Sandbanks": {
          "runnerId": 1953359195120116,
          "back": 0,
          "lay": 0
        },
        "8 Hasty Brook": {
          "runnerId": 1953359195180016,
          "back": 12.5,
          "lay": 0
        },
        "9 Just Alchemist": {
          "runnerId": 1953359195210016,
          "back": 2.62,
          "lay": 0
        },
        "10 Kool Kal": {
          "runnerId": 1953359195240016,
          "back": 4.2,
          "lay": 0
        },
        "13 Malinas Glory": {
          "runnerId": 1953359195350116,
          "back": 10.5,
          "lay": 0
        },
        "14 Money Heist": {
          "runnerId": 1953359195390016,
          "back": 0,
          "lay": 0
        },
        "15 Ned The Smith": {
          "runnerId": 1953359195420016,
          "back": 0,
          "lay": 0
        },
        "16 Silverstrand": {
          "runnerId": 1953359195450016,
          "back": 7,
          "lay": 0
        },
        "17 Sphagnum": {
          "runnerId": 1953359195480016,
          "back": 2.62,
          "lay": 0
        },
        "18 Rip Wendy": {
          "runnerId": 1953359195510116,
          "back": 2.62,
          "lay": 0
        },
        "19 Garcon Doux": {
          "runnerId": 1953359195540116,
          "back": 7,
          "lay": 0
        },
        "20 Royal Sage": {
          "runnerId": 1953359195580016,
          "back": 0,
          "lay": 0
        }
      }
    },
    "13:00 Newcastle": {
      "id": 1953362710950016,
      "start": "2022-01-06T13:00:00.000Z",
      "allRunners": {
        "5 Lord Paramount": {
          "runnerId": 1953362711960016,
          "back": 2.86,
          "lay": 3.75
        },
        "7 Sen Ding": {
          "runnerId": 1953362712020016,
          "back": 3.45,
          "lay": 0
        },
        "6 Roamin In Gloamin": {
          "runnerId": 1953362711990016,
          "back": 4.9,
          "lay": 12
        },
        "2 Barbara's Incharge": {
          "runnerId": 1953362711860016,
          "back": 10.5,
          "lay": 23
        },
        "1 Annaf": {
          "runnerId": 1953362711830016,
          "back": 11.5,
          "lay": 0
        },
        "4 Beneficiary": {
          "runnerId": 1953362711930016,
          "back": 9.6,
          "lay": 18.5
        },
        "3 Beattie Is Back": {
          "runnerId": 1953362711890116,
          "back": 10.5,
          "lay": 95
        },
        "8 Do I Dream": {
          "runnerId": 1953362712050116,
          "back": 4.4,
          "lay": 0
        },
        "9 Hello Power": {
          "runnerId": 1953362712080116,
          "back": 9.6,
          "lay": 0
        },
        "10 Lilywhite": {
          "runnerId": 1953362712110116,
          "back": 46,
          "lay": 0
        },
        "11 Penway": {
          "runnerId": 1953362712140116,
          "back": 4.2,
          "lay": 0
        },
        "12 Vamos Chica": {
          "runnerId": 1953362712180016,
          "back": 7,
          "lay": 0
        }
      }
    },
    "13:10 Chepstow": {
      "id": 1953363318660016,
      "start": "2022-01-06T13:10:00.000Z",
      "allRunners": {
        "3 Drenagh": {
          "runnerId": 1953363319590016,
          "back": 3.05,
          "lay": 4.8
        },
        "4 Hatos": {
          "runnerId": 1953363319620016,
          "back": 3.3,
          "lay": 0
        },
        "1 Ballybeen": {
          "runnerId": 1953363319520016,
          "back": 2.44,
          "lay": 4.3
        },
        "9 Petty Cash": {
          "runnerId": 1953363319780016,
          "back": 9.4,
          "lay": 16.5
        },
        "2 Captain Grinnaway": {
          "runnerId": 1953363319550116,
          "back": 0,
          "lay": 0
        },
        "5 Hesbehindyou": {
          "runnerId": 1953363319650116,
          "back": 6.6,
          "lay": 0
        },
        "6 Lucky Bounce": {
          "runnerId": 1953363319690016,
          "back": 6.6,
          "lay": 0
        },
        "7 Parsons Pleasure": {
          "runnerId": 1953363319720016,
          "back": 5.8,
          "lay": 0
        },
        "8 Patient Owner": {
          "runnerId": 1953363319750016,
          "back": 15,
          "lay": 780
        },
        "10 Roger Rarebit": {
          "runnerId": 1953363319810016,
          "back": 6,
          "lay": 0
        },
        "11 Shot Boii": {
          "runnerId": 1953363319840016,
          "back": 4.2,
          "lay": 0
        },
        "12 Beat The Storm": {
          "runnerId": 1953363319870016,
          "back": 0,
          "lay": 0
        }
      }
    },
    "13:20 Clonmel": {
      "id": 1953359198790016,
      "start": "2022-01-06T13:20:00.000Z",
      "allRunners": {
        "3 My Boy Bob": {
          "runnerId": 1953359200040116,
          "back": 2.3,
          "lay": 3.3
        },
        "4 Belle Lurette": {
          "runnerId": 1953359200070116,
          "back": 5.9,
          "lay": 9
        },
        "8 Brilliant Question": {
          "runnerId": 1953359200190016,
          "back": 10.5,
          "lay": 75
        },
        "1 Shantou Sisu": {
          "runnerId": 1953359199980016,
          "back": 5.3,
          "lay": 990
        },
        "2 Dicey Rylee": {
          "runnerId": 1953359200010116,
          "back": 4.6,
          "lay": 0
        },
        "5 Plentiful": {
          "runnerId": 1953359200100116,
          "back": 3.55,
          "lay": 0
        },
        "6 Time Budget": {
          "runnerId": 1953359200130016,
          "back": 6,
          "lay": 0
        },
        "7 We'llhavewan": {
          "runnerId": 1953359200160016,
          "back": 4.4,
          "lay": 0
        },
        "9 Condarcia": {
          "runnerId": 1953359200220016,
          "back": 4.2,
          "lay": 960
        },
        "10 Lesssaidthebetter": {
          "runnerId": 1953359200250016,
          "back": 5.6,
          "lay": 12
        },
        "11 Johanna Yeats": {
          "runnerId": 1953359200270116,
          "back": 11,
          "lay": 710
        },
        "12 Trans Wood": {
          "runnerId": 1953359200300116,
          "back": 4.4,
          "lay": 0
        },
        "13 It's Time Again": {
          "runnerId": 1953359200330016,
          "back": 4.6,
          "lay": 0
        },
        "14 Sienne D'or": {
          "runnerId": 1953359200360016,
          "back": 8.6,
          "lay": 0
        }
      }
    },
    "13:20 Vaal": {
      "id": 1954117807820016,
      "start": "2022-01-06T13:20:00.000Z",
      "allRunners": {
        "1 Bella Chica": {
          "runnerId": 1954117808670016,
          "back": 0,
          "lay": 0
        },
        "2 Before The Dawn": {
          "runnerId": 1954117808700016,
          "back": 0,
          "lay": 0
        },
        "3 Cold Fact": {
          "runnerId": 1954117808740016,
          "back": 0,
          "lay": 0
        },
        "4 Herstel": {
          "runnerId": 1954117808770016,
          "back": 0,
          "lay": 0
        },
        "5 Seemyvision": {
          "runnerId": 1954117808800016,
          "back": 0,
          "lay": 0
        },
        "6 Impressive Duchess": {
          "runnerId": 1954117808840016,
          "back": 0,
          "lay": 0
        },
        "7 Glowtoria": {
          "runnerId": 1954117808870016,
          "back": 0,
          "lay": 0
        },
        "8 Muleta": {
          "runnerId": 1954117808900116,
          "back": 0,
          "lay": 0
        },
        "9 Big Eyed Girl": {
          "runnerId": 1954117808930016,
          "back": 0,
          "lay": 0
        },
        "10 Alabama Anna": {
          "runnerId": 1954117808960016,
          "back": 0,
          "lay": 0
        },
        "11 There She Goes": {
          "runnerId": 1954117808980116,
          "back": 0,
          "lay": 0
        },
        "12 Milan's Princess": {
          "runnerId": 1954117809010016,
          "back": 0,
          "lay": 0
        }
      }
    },
    "13:30 Newcastle": {
      "id": 1953362712730016,
      "start": "2022-01-06T13:30:00.000Z",
      "allRunners": {
        "6 Aye Catcher": {
          "runnerId": 1953362713600116,
          "back": 5,
          "lay": 0
        },
        "8 Pink Storm": {
          "runnerId": 1953362713660116,
          "back": 7.4,
          "lay": 12
        },
        "1 Sassy Rascal": {
          "runnerId": 1953362713450016,
          "back": 3.6,
          "lay": 8.4
        },
        "9 Lunasa": {
          "runnerId": 1953362713690116,
          "back": 9.2,
          "lay": 0
        },
        "2 Dusky Prince": {
          "runnerId": 1953362713480016,
          "back": 8.6,
          "lay": 120
        },
        "3 Lucky Man": {
          "runnerId": 1953362713510016,
          "back": 2.86,
          "lay": 12
        },
        "4 Lucy Lulu": {
          "runnerId": 1953362713540116,
          "back": 0,
          "lay": 0
        },
        "5 Romantic Thought": {
          "runnerId": 1953362713570116,
          "back": 8.6,
          "lay": 1000
        },
        "7 Eesha Meesh": {
          "runnerId": 1953362713640016,
          "back": 12,
          "lay": 0
        },
        "10 Doomsday": {
          "runnerId": 1953362713720016,
          "back": 11,
          "lay": 75
        }
      }
    },
    "13:40 Chepstow": {
      "id": 1953363320360016,
      "start": "2022-01-06T13:40:00.000Z",
      "allRunners": {
        "1 Ask A Honey Bee": {
          "runnerId": 1953363320730016,
          "back": 1.1,
          "lay": 1.14
        },
        "3 Captain Cuckoo": {
          "runnerId": 1953363320790116,
          "back": 9.8,
          "lay": 16.5
        },
        "4 Coalbrook Bridge": {
          "runnerId": 1953363320820116,
          "back": 8,
          "lay": 0
        },
        "2 Barnaviddaun": {
          "runnerId": 1953363320760116,
          "back": 0,
          "lay": 0
        }
      }
    },
    "13:50 Clonmel": {
      "id": 1953359202700016,
      "start": "2022-01-06T13:50:00.000Z",
      "allRunners": {
        "5 Classic Getaway": {
          "runnerId": 1953359203310016,
          "back": 1.81,
          "lay": 2.24
        },
        "4 Uhtred": {
          "runnerId": 1953359203270116,
          "back": 5.6,
          "lay": 13
        },
        "2 Gordon Dai Dai": {
          "runnerId": 1953359203210116,
          "back": 6.8,
          "lay": 9.8
        },
        "1 Cash Back": {
          "runnerId": 1953359203180016,
          "back": 5.6,
          "lay": 11
        },
        "3 Rodaniche": {
          "runnerId": 1953359203240116,
          "back": 12,
          "lay": 110
        }
      }
    },
    "13:55 Vaal": {
      "id": 1954117809510016,
      "start": "2022-01-06T13:55:00.000Z",
      "allRunners": {
        "1 Bathing Beauty": {
          "runnerId": 1954117810450016,
          "back": 0,
          "lay": 0
        },
        "2 Captain's Run": {
          "runnerId": 1954117810480016,
          "back": 0,
          "lay": 0
        },
        "3 On Cue": {
          "runnerId": 1954117810510016,
          "back": 0,
          "lay": 0
        },
        "4 Stolen Kiss": {
          "runnerId": 1954117810540116,
          "back": 0,
          "lay": 0
        },
        "5 Gin And Tonic": {
          "runnerId": 1954117810580016,
          "back": 0,
          "lay": 0
        },
        "6 Verinova": {
          "runnerId": 1954117810610016,
          "back": 0,
          "lay": 0
        },
        "7 Vuitton": {
          "runnerId": 1954117810640116,
          "back": 0,
          "lay": 0
        },
        "8 Rozara": {
          "runnerId": 1954117810680016,
          "back": 0,
          "lay": 0
        },
        "9 Veneta": {
          "runnerId": 1954117810710016,
          "back": 0,
          "lay": 0
        },
        "10 Hear The Trumpet": {
          "runnerId": 1954117810740116,
          "back": 0,
          "lay": 0
        },
        "11 Samoa": {
          "runnerId": 1954117810780016,
          "back": 0,
          "lay": 0
        },
        "12 Allez Les Bleu": {
          "runnerId": 1954117810810016,
          "back": 0,
          "lay": 0
        },
        "13 Mercer Girl": {
          "runnerId": 1954117810850016,
          "back": 0,
          "lay": 0
        }
      }
    },
    "14:00 Newcastle": {
      "id": 1953362714190016,
      "start": "2022-01-06T14:00:00.000Z",
      "allRunners": {
        "3 Simple Star": {
          "runnerId": 1953362714580116,
          "back": 5,
          "lay": 9
        },
        "4 Galidermes": {
          "runnerId": 1953362714610116,
          "back": 10.5,
          "lay": 15
        },
        "1 Desert Emperor": {
          "runnerId": 1953362714530016,
          "back": 1.37,
          "lay": 2.28
        },
        "2 Society Red": {
          "runnerId": 1953362714560016,
          "back": 3.6,
          "lay": 4.8
        }
      }
    },
    "14:15 Chepstow": {
      "id": 1953363321100016,
      "start": "2022-01-06T14:15:00.000Z",
      "allRunners": {
        "5 Largy Nights": {
          "runnerId": 1953363321820116,
          "back": 7.2,
          "lay": 900
        },
        "1 Crossing Lines": {
          "runnerId": 1953363321700016,
          "back": 4.3,
          "lay": 7.8
        },
        "2 Dom Of Mary": {
          "runnerId": 1953363321730016,
          "back": 2.92,
          "lay": 3.1
        },
        "3 Helios De Grugy": {
          "runnerId": 1953363321760116,
          "back": 7.6,
          "lay": 0
        },
        "4 Jukebox Junior": {
          "runnerId": 1953363321790116,
          "back": 4.6,
          "lay": 0
        },
        "6 Mahon Point": {
          "runnerId": 1953363321860016,
          "back": 2.62,
          "lay": 3.2
        },
        "7 Sam's The Man": {
          "runnerId": 1953363321880116,
          "back": 4.6,
          "lay": 160
        },
        "8 Tis But A Scratch": {
          "runnerId": 1953363321910116,
          "back": 7.2,
          "lay": 0
        }
      }
    },
    "14:25 Clonmel": {
      "id": 1953359204980016,
      "start": "2022-01-06T14:25:00.000Z",
      "allRunners": {
        "13 Falco Du Sauzay": {
          "runnerId": 1953359206550116,
          "back": 12.5,
          "lay": 0
        },
        "6 Close Enough": {
          "runnerId": 1953359206350016,
          "back": 4.2,
          "lay": 0
        },
        "1 Full Noise": {
          "runnerId": 1953359206190016,
          "back": 1.46,
          "lay": 3.15
        },
        "2 The Higher Road": {
          "runnerId": 1953359206220116,
          "back": 4.5,
          "lay": 65
        },
        "3 Ardera Ru": {
          "runnerId": 1953359206250116,
          "back": 3.45,
          "lay": 0
        },
        "4 Coole Arcade": {
          "runnerId": 1953359206290016,
          "back": 5.1,
          "lay": 14
        },
        "5 Steelers Appeal": {
          "runnerId": 1953359206320016,
          "back": 14.5,
          "lay": 0
        },
        "7 Betterask Jj": {
          "runnerId": 1953359206380016,
          "back": 11,
          "lay": 0
        },
        "8 Jennys Grey": {
          "runnerId": 1953359206410016,
          "back": 4.2,
          "lay": 0
        },
        "10 Happy Dancing": {
          "runnerId": 1953359206460116,
          "back": 6.8,
          "lay": 0
        },
        "11 Mrs Watson": {
          "runnerId": 1953359206490116,
          "back": 12.5,
          "lay": 95
        },
        "12 Costalita": {
          "runnerId": 1953359206520116,
          "back": 4.3,
          "lay": 0
        },
        "14 Some Venture": {
          "runnerId": 1953359206580116,
          "back": 4.5,
          "lay": 0
        },
        "9 Sweet Will": {
          "runnerId": 1953359206440016,
          "back": 0,
          "lay": 0
        }
      }
    },
    "14:35 Newcastle": {
      "id": 1953362714860016,
      "start": "2022-01-06T14:35:00.000Z",
      "allRunners": {
        "2 Spartan Fighter": {
          "runnerId": 1953362715310016,
          "back": 2.6,
          "lay": 4.5
        },
        "4 Sir Maxi": {
          "runnerId": 1953362715370016,
          "back": 3.7,
          "lay": 4.9
        },
        "5 Millionaire Waltz": {
          "runnerId": 1953362715390116,
          "back": 6.2,
          "lay": 9
        },
        "3 Dutch Decoy": {
          "runnerId": 1953362715340016,
          "back": 5.1,
          "lay": 6.4
        },
        "1 Sanaadh": {
          "runnerId": 1953362715270116,
          "back": 6.8,
          "lay": 0
        }
      }
    },
    "14:50 Chepstow": {
      "id": 1953363322290016,
      "start": "2022-01-06T14:50:00.000Z",
      "allRunners": {
        "2 Galop De Chasse": {
          "runnerId": 1953363322960116,
          "back": 3,
          "lay": 3.3
        },
        "1 Can You Call": {
          "runnerId": 1953363322930016,
          "back": 3,
          "lay": 4
        },
        "8 Billingsley": {
          "runnerId": 1953363323140016,
          "back": 8.2,
          "lay": 12
        },
        "6 Rose Sea Has": {
          "runnerId": 1953363323080116,
          "back": 17,
          "lay": 0
        },
        "3 Early Du Lemo": {
          "runnerId": 1953363322990116,
          "back": 7,
          "lay": 24
        },
        "4 Gingembre Menthe": {
          "runnerId": 1953363323020116,
          "back": 11.5,
          "lay": 0
        },
        "5 Le Coeur Net": {
          "runnerId": 1953363323050116,
          "back": 15,
          "lay": 42
        },
        "7 Le Ligerien": {
          "runnerId": 1953363323110116,
          "back": 11.5,
          "lay": 22
        }
      }
    },
    "15:00 Clonmel": {
      "id": 1953359208730016,
      "start": "2022-01-06T15:00:00.000Z",
      "allRunners": {
        "5 Carnet De Stage": {
          "runnerId": 1953359209840116,
          "back": 4,
          "lay": 5
        },
        "6 An Marcach": {
          "runnerId": 1953359209870016,
          "back": 11.5,
          "lay": 21
        },
        "9 Fiston Du Mou": {
          "runnerId": 1953359209960116,
          "back": 8.6,
          "lay": 0
        },
        "1 Presenting Dylan": {
          "runnerId": 1953359209720016,
          "back": 9,
          "lay": 75
        },
        "2 Itsalonglongroad": {
          "runnerId": 1953359209750016,
          "back": 11,
          "lay": 0
        },
        "3 Nelly's Money": {
          "runnerId": 1953359209780016,
          "back": 12.5,
          "lay": 80
        },
        "4 Spare Brakes": {
          "runnerId": 1953359209810016,
          "back": 12,
          "lay": 0
        },
        "7 Seangoell": {
          "runnerId": 1953359209900016,
          "back": 11.5,
          "lay": 0
        },
        "8 Tipping Away": {
          "runnerId": 1953359209930116,
          "back": 11.5,
          "lay": 0
        },
        "10 Fox Le Bel": {
          "runnerId": 1953359209990116,
          "back": 5.6,
          "lay": 0
        },
        "11 Bitview Colin": {
          "runnerId": 1953359210020116,
          "back": 3.55,
          "lay": 0
        },
        "12 Hollybank King": {
          "runnerId": 1953359210050116,
          "back": 4.5,
          "lay": 34
        }
      }
    },
    "15:10 Newcastle": {
      "id": 1953362715710016,
      "start": "2022-01-06T15:10:00.000Z",
      "allRunners": {
        "10 Zenzero": {
          "runnerId": 1953362716990116,
          "back": 7.2,
          "lay": 27
        },
        "9 Bobby Joe Leg": {
          "runnerId": 1953362716960116,
          "back": 8.6,
          "lay": 36
        },
        "3 Whatzupwithme": {
          "runnerId": 1953362716790016,
          "back": 11.5,
          "lay": 100
        },
        "1 Mashaan": {
          "runnerId": 1953362716730016,
          "back": 11.5,
          "lay": 42
        },
        "2 Harvest Day": {
          "runnerId": 1953362716760016,
          "back": 4.5,
          "lay": 11
        },
        "4 Abnaa": {
          "runnerId": 1953362716820016,
          "back": 6,
          "lay": 10
        },
        "5 Pallas Lord": {
          "runnerId": 1953362716840116,
          "back": 6.4,
          "lay": 8.6
        },
        "6 Mabdaa": {
          "runnerId": 1953362716870016,
          "back": 12.5,
          "lay": 0
        },
        "7 Palazzo": {
          "runnerId": 1953362716900016,
          "back": 11.5,
          "lay": 0
        },
        "8 Wabbal": {
          "runnerId": 1953362716930116,
          "back": 9.2,
          "lay": 65
        },
        "11 The Mackem Torpedo": {
          "runnerId": 1953362717020016,
          "back": 13,
          "lay": 70
        },
        "12 Power Player": {
          "runnerId": 1953362717050016,
          "back": 15.5,
          "lay": 950
        },
        "13 Perfect Soldier": {
          "runnerId": 1953362717080016,
          "back": 21,
          "lay": 0
        },
        "14 Elspeth Rose": {
          "runnerId": 1953362717110016,
          "back": 7,
          "lay": 0
        }
      }
    },
    "15:20 Chepstow": {
      "id": 1953363323550016,
      "start": "2022-01-06T15:20:00.000Z",
      "allRunners": {
        "4 Helios Allen": {
          "runnerId": 1953363324480016,
          "back": 2.82,
          "lay": 3.55
        },
        "5 Garincha": {
          "runnerId": 1953363324510016,
          "back": 4.7,
          "lay": 8
        },
        "6 Caswell Bay": {
          "runnerId": 1953363324540016,
          "back": 5.9,
          "lay": 9.6
        },
        "8 Straight Swap": {
          "runnerId": 1953363324600016,
          "back": 7,
          "lay": 27
        },
        "10 Kenny George": {
          "runnerId": 1953363324660016,
          "back": 11.5,
          "lay": 27
        },
        "1 Point Of Principle": {
          "runnerId": 1953363324380016,
          "back": 20,
          "lay": 0
        },
        "2 Affoburg": {
          "runnerId": 1953363324410116,
          "back": 15.5,
          "lay": 1000
        },
        "3 Lydford Lad": {
          "runnerId": 1953363324450016,
          "back": 16.5,
          "lay": 80
        },
        "7 Voyage De Retour": {
          "runnerId": 1953363324570116,
          "back": 13,
          "lay": 85
        },
        "9 Jaunty Viking": {
          "runnerId": 1953363324630016,
          "back": 14,
          "lay": 450
        },
        "11 Akkapenko": {
          "runnerId": 1953363324690016,
          "back": 10,
          "lay": 0
        }
      }
    },
    "15:30 Clonmel": {
      "id": 1953359212100016,
      "start": "2022-01-06T15:30:00.000Z",
      "allRunners": {
        "1 Ask D'man": {
          "runnerId": 1953359213110016,
          "back": 2.9,
          "lay": 34
        },
        "11 Midway To Getaway": {
          "runnerId": 1953359213420016,
          "back": 6.8,
          "lay": 36
        },
        "2 Chato Santana": {
          "runnerId": 1953359213140116,
          "back": 4.2,
          "lay": 0
        },
        "3 Cloudy Wednesday": {
          "runnerId": 1953359213180016,
          "back": 7,
          "lay": 0
        },
        "4 Handy Headon": {
          "runnerId": 1953359213200116,
          "back": 12.5,
          "lay": 0
        },
        "5 I Often Wonder": {
          "runnerId": 1953359213240016,
          "back": 5.9,
          "lay": 0
        },
        "6 Is A Real Champ": {
          "runnerId": 1953359213270016,
          "back": 2.72,
          "lay": 0
        },
        "7 Three Loud Knocks": {
          "runnerId": 1953359213290116,
          "back": 4.2,
          "lay": 0
        },
        "8 Time To Bite": {
          "runnerId": 1953359213320116,
          "back": 4.4,
          "lay": 0
        },
        "9 Aghmorough Bridge": {
          "runnerId": 1953359213350116,
          "back": 11.5,
          "lay": 0
        },
        "10 Call Me Merry": {
          "runnerId": 1953359213390016,
          "back": 4.6,
          "lay": 0
        }
      }
    },
    "15:40 Newcastle": {
      "id": 1953362717710016,
      "start": "2022-01-06T15:40:00.000Z",
      "allRunners": {
        "2 Cephalus": {
          "runnerId": 1953362718120116,
          "back": 2.22,
          "lay": 2.6
        },
        "1 Devasboy": {
          "runnerId": 1953362718100016,
          "back": 3.8,
          "lay": 6
        },
        "4 Sparka": {
          "runnerId": 1953362718180116,
          "back": 6.6,
          "lay": 22
        },
        "3 Novak": {
          "runnerId": 1953362718150116,
          "back": 4.6,
          "lay": 0
        },
        "5 Maggie's Joy": {
          "runnerId": 1953362718220016,
          "back": 10,
          "lay": 0
        }
      }
    },
    "15:50 Chepstow": {
      "id": 1953363325180016,
      "start": "2022-01-06T15:50:00.000Z",
      "allRunners": {
        "4 Gemirande": {
          "runnerId": 1953363326030016,
          "back": 3.05,
          "lay": 0
        },
        "6 Destin D'Ajonc": {
          "runnerId": 1953363326090016,
          "back": 5.5,
          "lay": 5.7
        },
        "8 Mouseinthehouse": {
          "runnerId": 1953363326160016,
          "back": 8.2,
          "lay": 11
        },
        "3 Thomas Patrick": {
          "runnerId": 1953363325990116,
          "back": 11.5,
          "lay": 20
        },
        "5 Enormouse": {
          "runnerId": 1953363326060016,
          "back": 12,
          "lay": 48
        },
        "1 Broken Quest": {
          "runnerId": 1953363325930016,
          "back": 7.6,
          "lay": 24
        },
        "2 The Mighty Arc": {
          "runnerId": 1953363325960116,
          "back": 4.8,
          "lay": 8
        },
        "7 Lord Bryan": {
          "runnerId": 1953363326120116,
          "back": 12,
          "lay": 60
        },
        "9 El Hageb Rose": {
          "runnerId": 1953363326190016,
          "back": 11,
          "lay": 95
        }
      }
    },
    "16:00 Chelmsford": {
      "id": 1953363622150016,
      "start": "2022-01-06T16:00:00.000Z",
      "allRunners": {
        "3 Almaan": {
          "runnerId": 1953363622990116,
          "back": 5.1,
          "lay": 7
        },
        "7 Healing Power": {
          "runnerId": 1953363623120016,
          "back": 7.6,
          "lay": 48
        },
        "1 Alhammaam": {
          "runnerId": 1953363622930016,
          "back": 3.2,
          "lay": 3.4
        },
        "2 Battle Of Marathon": {
          "runnerId": 1953363622960116,
          "back": 11,
          "lay": 0
        },
        "4 El Camino": {
          "runnerId": 1953363623020116,
          "back": 9.4,
          "lay": 15
        },
        "5 Woke Media": {
          "runnerId": 1953363623050116,
          "back": 9.4,
          "lay": 0
        },
        "6 Seesawing": {
          "runnerId": 1953363623090016,
          "back": 3.95,
          "lay": 0
        },
        "8 Tie A Yellowribbon": {
          "runnerId": 1953363623150016,
          "back": 9.6,
          "lay": 18
        }
      }
    },
    "16:30 Chelmsford": {
      "id": 1953363625370016,
      "start": "2022-01-06T16:30:00.000Z",
      "allRunners": {
        "9 No Diggity": {
          "runnerId": 1953363626600016,
          "back": 3.95,
          "lay": 12
        },
        "1 Crazy Spin": {
          "runnerId": 1953363626350016,
          "back": 3.8,
          "lay": 24
        },
        "2 Disarming": {
          "runnerId": 1953363626380016,
          "back": 8.6,
          "lay": 22
        },
        "3 Essgee Nics": {
          "runnerId": 1953363626410016,
          "back": 9.6,
          "lay": 60
        },
        "4 Ethel C": {
          "runnerId": 1953363626440016,
          "back": 7.6,
          "lay": 0
        },
        "5 Farewell Kiss": {
          "runnerId": 1953363626470016,
          "back": 4.4,
          "lay": 0
        },
        "6 Ivahunch": {
          "runnerId": 1953363626500016,
          "back": 6.6,
          "lay": 0
        },
        "7 Laurentia": {
          "runnerId": 1953363626530116,
          "back": 4.3,
          "lay": 10
        },
        "8 Maeve's Memory": {
          "runnerId": 1953363626560116,
          "back": 6,
          "lay": 0
        },
        "10 Pips Tune": {
          "runnerId": 1953363626630016,
          "back": 8.2,
          "lay": 18
        },
        "11 Recuerdame": {
          "runnerId": 1953363626660016,
          "back": 5.9,
          "lay": 12.5
        }
      }
    },
    "17:00 Chelmsford": {
      "id": 1953363629440016,
      "start": "2022-01-06T17:00:00.000Z",
      "allRunners": {
        "2 Vignoni": {
          "runnerId": 1953363630210016,
          "back": 2.22,
          "lay": 3.3
        },
        "1 Gordonontheorgan": {
          "runnerId": 1953363630180016,
          "back": 4,
          "lay": 0
        },
        "3 Are You Able": {
          "runnerId": 1953363630230116,
          "back": 3.85,
          "lay": 0
        },
        "4 Daruan": {
          "runnerId": 1953363630260116,
          "back": 3.55,
          "lay": 0
        },
        "5 Dark Flyer": {
          "runnerId": 1953363630290016,
          "back": 5.1,
          "lay": 22
        },
        "6 Depart A Minuit": {
          "runnerId": 1953363630320016,
          "back": 3.8,
          "lay": 20
        },
        "7 No Fear Lucy": {
          "runnerId": 1953363630350016,
          "back": 8.2,
          "lay": 0
        },
        "8 T Maxie": {
          "runnerId": 1953363630370116,
          "back": 2.52,
          "lay": 0
        }
      }
    },
    "17:30 Chelmsford": {
      "id": 1953363636660016,
      "start": "2022-01-06T17:30:00.000Z",
      "allRunners": {
        "3 Split Elevens": {
          "runnerId": 1953363637680016,
          "back": 5.1,
          "lay": 0
        },
        "1 Secret To Success": {
          "runnerId": 1953363637610016,
          "back": 7.2,
          "lay": 14.5
        },
        "2 Macs Dilemma": {
          "runnerId": 1953363637640116,
          "back": 3.15,
          "lay": 0
        },
        "4 Dors Toyboy": {
          "runnerId": 1953363637710016,
          "back": 5.2,
          "lay": 12
        },
        "5 Havergate Island": {
          "runnerId": 1953363637740016,
          "back": 11,
          "lay": 0
        },
        "6 Twentysharesofgrey": {
          "runnerId": 1953363637770016,
          "back": 7.6,
          "lay": 11
        },
        "7 Blackthirtyone": {
          "runnerId": 1953363637800116,
          "back": 14,
          "lay": 970
        },
        "8 Rinty Maginty": {
          "runnerId": 1953363637830116,
          "back": 11,
          "lay": 0
        },
        "9 Closeness": {
          "runnerId": 1953363637860116,
          "back": 6.6,
          "lay": 0
        },
        "10 You Missed Her": {
          "runnerId": 1953363637940016,
          "back": 11.5,
          "lay": 0
        },
        "11 The Game Of Life": {
          "runnerId": 1953363637970116,
          "back": 4.6,
          "lay": 950
        }
      }
    },
    "18:00 Chelmsford": {
      "id": 1953363639940016,
      "start": "2022-01-06T18:00:00.000Z",
      "allRunners": {
        "3 Shadow Angel": {
          "runnerId": 1953363640840016,
          "back": 7,
          "lay": 9
        },
        "1 River Chorus": {
          "runnerId": 1953363640780016,
          "back": 4.8,
          "lay": 7.2
        },
        "2 Hot Romance": {
          "runnerId": 1953363640810016,
          "back": 11.5,
          "lay": 80
        },
        "4 Trepidation": {
          "runnerId": 1953363640870016,
          "back": 4.3,
          "lay": 7.2
        },
        "5 Perfect Symphony": {
          "runnerId": 1953363640900016,
          "back": 5.7,
          "lay": 0
        },
        "6 Arlo's Sunshine": {
          "runnerId": 1953363640930016,
          "back": 4.8,
          "lay": 9
        },
        "7 Edessann": {
          "runnerId": 1953363640960116,
          "back": 12,
          "lay": 170
        },
        "8 Kraka": {
          "runnerId": 1953363640990116,
          "back": 12,
          "lay": 95
        },
        "9 Vino Santo": {
          "runnerId": 1953363641030016,
          "back": 7.4,
          "lay": 1000
        },
        "10 Woo Woo": {
          "runnerId": 1953363641060016,
          "back": 6.6,
          "lay": 0
        }
      }
    },
    "18:30 Chelmsford": {
      "id": 1953363642960016,
      "start": "2022-01-06T18:30:00.000Z",
      "allRunners": {
        "3 Della Mare": {
          "runnerId": 1953363644190016,
          "back": 4.1,
          "lay": 6.8
        },
        "6 Krazy Paving": {
          "runnerId": 1953363644280016,
          "back": 8.6,
          "lay": 0
        },
        "1 Brazen Arrow": {
          "runnerId": 1953363644120016,
          "back": 8.6,
          "lay": 260
        },
        "2 But You Said": {
          "runnerId": 1953363644160016,
          "back": 6.2,
          "lay": 65
        },
        "5 Knockabout Queen": {
          "runnerId": 1953363644250016,
          "back": 9.6,
          "lay": 0
        },
        "7 Lady Monica": {
          "runnerId": 1953363644310116,
          "back": 0,
          "lay": 0
        },
        "8 Monsieur Fantaisie": {
          "runnerId": 1953363644340016,
          "back": 3.55,
          "lay": 5.2
        },
        "9 Moveonup": {
          "runnerId": 1953363644370016,
          "back": 11.5,
          "lay": 0
        },
        "10 Nozieres": {
          "runnerId": 1953363644400016,
          "back": 0,
          "lay": 0
        },
        "11 Red Allure": {
          "runnerId": 1953363644420116,
          "back": 11.5,
          "lay": 0
        },
        "13 Vincenzo Coccotti": {
          "runnerId": 1953363644480016,
          "back": 11.5,
          "lay": 0
        },
        "4 Indian Affair": {
          "runnerId": 1953363644220116,
          "back": 0,
          "lay": 0
        },
        "12 Rockesbury": {
          "runnerId": 1953363644450016,
          "back": 0,
          "lay": 0
        }
      }
    },
    "19:00 Chelmsford": {
      "id": 1953363646540016,
      "start": "2022-01-06T19:00:00.000Z",
      "allRunners": {
        "2 Elmejor": {
          "runnerId": 1953363647480016,
          "back": 5.6,
          "lay": 14
        },
        "3 Qeyaady": {
          "runnerId": 1953363647510016,
          "back": 3.55,
          "lay": 0
        },
        "1 Mighty Power": {
          "runnerId": 1953363647450016,
          "back": 9.4,
          "lay": 14.5
        },
        "4 Semser": {
          "runnerId": 1953363647540016,
          "back": 3.9,
          "lay": 21
        },
        "5 Majestic Tejaan": {
          "runnerId": 1953363647570016,
          "back": 11,
          "lay": 27
        },
        "6 Pledge Of Honour": {
          "runnerId": 1953363647600016,
          "back": 3.8,
          "lay": 0
        },
        "7 Light Up Our Stars": {
          "runnerId": 1953363647630016,
          "back": 4.8,
          "lay": 18
        },
        "9 Bayston Hill": {
          "runnerId": 1953363647690016,
          "back": 9.6,
          "lay": 29
        },
        "10 Engrave": {
          "runnerId": 1953363647720016,
          "back": 9.6,
          "lay": 36
        },
        "8 Kentucky Kingdom": {
          "runnerId": 1953363647660016,
          "back": 0,
          "lay": 0
        }
      }
    },
    "19:30 Chelmsford": {
      "id": 1953363649630016,
      "start": "2022-01-06T19:30:00.000Z",
      "allRunners": {
        "2 Brass Clankers": {
          "runnerId": 1953363650540016,
          "back": 6.6,
          "lay": 9.2
        },
        "1 Born To Sire": {
          "runnerId": 1953363650510016,
          "back": 7.2,
          "lay": 34
        },
        "3 Kerrera": {
          "runnerId": 1953363650570016,
          "back": 0,
          "lay": 0
        },
        "4 Miss Sligo": {
          "runnerId": 1953363650600116,
          "back": 5.1,
          "lay": 90
        },
        "5 My Lady Claire": {
          "runnerId": 1953363650630016,
          "back": 8.2,
          "lay": 0
        },
        "6 Thunderoad": {
          "runnerId": 1953363650660016,
          "back": 7,
          "lay": 36
        },
        "7 Carmela Soprano": {
          "runnerId": 1953363650690116,
          "back": 8.6,
          "lay": 0
        },
        "8 Jeremiah Johnson": {
          "runnerId": 1953363650720116,
          "back": 5.6,
          "lay": 0
        },
        "9 Placated": {
          "runnerId": 1953363650750116,
          "back": 10.5,
          "lay": 46
        },
        "10 Roby Mill": {
          "runnerId": 1953363650780016,
          "back": 0,
          "lay": 0
        }
      }
    }
  }
}