{
  "id": 15,
  "events": {
    "Linares Deportivo vs FC Barcelona": {
      "id": 1949402852340016,
      "start": "2022-01-05T18:30:00.000Z",
      "allRunners": {
        "Linares Deportivo": {
          "runnerId": 1949402855860016,
          "back": 9.8,
          "lay": 11
        },
        "FC Barcelona": {
          "runnerId": 1949402855890116,
          "back": 1.36,
          "lay": 1.4
        },
        "DRAW (Lin/FC )": {
          "runnerId": 1949402855930016,
          "back": 5.5,
          "lay": 5.9
        }
      }
    },
    "Atlético Baleares vs Celta de Vigo": {
      "id": 1949402866360016,
      "start": "2022-01-05T19:00:00.000Z",
      "allRunners": {
        "Atlético Baleares": {
          "runnerId": 1949402869930116,
          "back": 5.3,
          "lay": 5.6
        },
        "Celta de Vigo": {
          "runnerId": 1949402869970016,
          "back": 1.79,
          "lay": 1.84
        },
        "DRAW (Atl/Cel)": {
          "runnerId": 1949402870000116,
          "back": 3.65,
          "lay": 3.85
        }
      }
    },
    "Mirandés vs Rayo Vallecano": {
      "id": 1949402900370016,
      "start": "2022-01-05T19:00:00.000Z",
      "allRunners": {
        "Mirandés": {
          "runnerId": 1949402904070016,
          "back": 4.2,
          "lay": 4.4
        },
        "Rayo Vallecano": {
          "runnerId": 1949402904110016,
          "back": 2.04,
          "lay": 2.1
        },
        "DRAW (Mir/Ray)": {
          "runnerId": 1949402904150016,
          "back": 3.45,
          "lay": 3.6
        }
      }
    },
    "Real Valladolid vs Real Betis": {
      "id": 1949402882510016,
      "start": "2022-01-05T19:00:00.000Z",
      "allRunners": {
        "Real Valladolid": {
          "runnerId": 1949402886460016,
          "back": 3.15,
          "lay": 3.25
        },
        "Real Betis": {
          "runnerId": 1949402886500116,
          "back": 2.38,
          "lay": 2.42
        },
        "DRAW (Rea/Rea)": {
          "runnerId": 1949402886540016,
          "back": 3.65,
          "lay": 3.9
        }
      }
    },
    "Taguatinga U20 vs Sport Club do Recife U20": {
      "id": 1953012464220016,
      "start": "2022-01-05T19:00:00.000Z",
      "allRunners": {
        "Taguatinga U20": {
          "runnerId": 1953012465810016,
          "back": 0,
          "lay": 0
        },
        "Sport Club do Recife U20": {
          "runnerId": 1953012465840116,
          "back": 0,
          "lay": 0
        },
        "DRAW (Tag/Spo)": {
          "runnerId": 1953012465880016,
          "back": 0,
          "lay": 0
        }
      }
    },
    "Panathinaikos vs Aris Thessaloniki": {
      "id": 1951299210670016,
      "start": "2022-01-05T19:30:00.000Z",
      "allRunners": {
        "Panathinaikos": {
          "runnerId": 1951299213570116,
          "back": 1.87,
          "lay": 1.96
        },
        "Aris Thessaloniki": {
          "runnerId": 1951299213610016,
          "back": 5.7,
          "lay": 6.4
        },
        "DRAW (Pan/Ari)": {
          "runnerId": 1951299213650016,
          "back": 3.1,
          "lay": 3.4
        }
      }
    },
    "Chelsea vs Tottenham Hotspur": {
      "id": 1942546357150016,
      "start": "2022-01-05T19:45:00.000Z",
      "allRunners": {
        "Chelsea": {
          "runnerId": 1942546358130116,
          "back": 1.95,
          "lay": 1.96
        },
        "Tottenham Hotspur": {
          "runnerId": 1942546358170016,
          "back": 4.7,
          "lay": 4.8
        },
        "DRAW (Che/Tot)": {
          "runnerId": 1942546358200016,
          "back": 3.6,
          "lay": 3.65
        }
      }
    },
    "EC Sao Bernardo U20 vs EC São Bento U20": {
      "id": 1953012400200016,
      "start": "2022-01-05T20:00:00.000Z",
      "allRunners": {
        "EC Sao Bernardo U20": {
          "runnerId": 1953012401700016,
          "back": 2,
          "lay": 2.46
        },
        "EC São Bento U20": {
          "runnerId": 1953012401760016,
          "back": 3.05,
          "lay": 4.1
        },
        "DRAW (EC /EC )": {
          "runnerId": 1953012401790116,
          "back": 3.35,
          "lay": 4.5
        }
      }
    },
    "Andira U20 vs Atlético Mineiro U20": {
      "id": 1953012471860016,
      "start": "2022-01-05T20:15:00.000Z",
      "allRunners": {
        "Andira U20": {
          "runnerId": 1953012473450116,
          "back": 0,
          "lay": 0
        },
        "Atlético Mineiro U20": {
          "runnerId": 1953012473490116,
          "back": 0,
          "lay": 0
        },
        "DRAW (And/Atl)": {
          "runnerId": 1953012473530116,
          "back": 0,
          "lay": 0
        }
      }
    },
    "Itapirense U20 vs Retro U20": {
      "id": 1953012408090016,
      "start": "2022-01-05T20:15:00.000Z",
      "allRunners": {
        "Itapirense U20": {
          "runnerId": 1953012409680016,
          "back": 2.84,
          "lay": 3.5
        },
        "Retro U20": {
          "runnerId": 1953012409720116,
          "back": 2.24,
          "lay": 2.58
        },
        "DRAW (Ita/Ret)": {
          "runnerId": 1953012409770016,
          "back": 3.25,
          "lay": 4.1
        }
      }
    },
    "Sao Caetano SP U20 vs Desportiva Perilima U20": {
      "id": 1953012413890016,
      "start": "2022-01-05T20:15:00.000Z",
      "allRunners": {
        "Sao Caetano SP U20": {
          "runnerId": 1953012415430116,
          "back": 1.73,
          "lay": 2.1
        },
        "Desportiva Perilima U20": {
          "runnerId": 1953012415470016,
          "back": 3.75,
          "lay": 5.2
        },
        "DRAW (Sao/Des)": {
          "runnerId": 1953012415510016,
          "back": 3.5,
          "lay": 4.8
        }
      }
    },
    "Alcoyano vs Real Madrid": {
      "id": 1949402838360016,
      "start": "2022-01-05T20:30:00.000Z",
      "allRunners": {
        "Alcoyano": {
          "runnerId": 1949402841900116,
          "back": 16,
          "lay": 22
        },
        "Real Madrid": {
          "runnerId": 1949402841940016,
          "back": 1.19,
          "lay": 1.2
        },
        "DRAW (Alc/Rea)": {
          "runnerId": 1949402841970116,
          "back": 8.4,
          "lay": 8.8
        }
      }
    },
    "Londrina U20 vs Aster Brasil U20": {
      "id": 1953012421710016,
      "start": "2022-01-05T22:15:00.000Z",
      "allRunners": {
        "Londrina U20": {
          "runnerId": 1953012423290116,
          "back": 0,
          "lay": 0
        },
        "Aster Brasil U20": {
          "runnerId": 1953012423330016,
          "back": 0,
          "lay": 0
        },
        "DRAW (Lon/Ast)": {
          "runnerId": 1953012423360116,
          "back": 0,
          "lay": 0
        }
      }
    },
    "Cruzeiro Futebol Clube U20 vs Palmas Futebol e Regatas U20": {
      "id": 1953012427620016,
      "start": "2022-01-05T22:30:00.000Z",
      "allRunners": {
        "Cruzeiro Futebol Clube U20": {
          "runnerId": 1953012429170016,
          "back": 1.1,
          "lay": 1.14
        },
        "Palmas Futebol e Regatas U20": {
          "runnerId": 1953012429210016,
          "back": 0,
          "lay": 0
        },
        "DRAW (Cru/Pal)": {
          "runnerId": 1953012429240116,
          "back": 0,
          "lay": 0
        }
      }
    },
    "Oeste FC U20 vs Floresta EC U20": {
      "id": 1953012437370016,
      "start": "2022-01-05T22:30:00.000Z",
      "allRunners": {
        "Oeste FC U20": {
          "runnerId": 1953012438890016,
          "back": 0,
          "lay": 0
        },
        "Floresta EC U20": {
          "runnerId": 1953012438920116,
          "back": 0,
          "lay": 0
        },
        "DRAW (Oes/Flo)": {
          "runnerId": 1953012438960116,
          "back": 0,
          "lay": 0
        }
      }
    },
    "São Paulo U20 vs Clube Sociedade Esportiva U20": {
      "id": 1953012431110016,
      "start": "2022-01-05T22:30:00.000Z",
      "allRunners": {
        "São Paulo U20": {
          "runnerId": 1953012432650016,
          "back": 0,
          "lay": 0
        },
        "Clube Sociedade Esportiva U20": {
          "runnerId": 1953012432680116,
          "back": 0,
          "lay": 0
        },
        "DRAW (São/Clu)": {
          "runnerId": 1953012432720016,
          "back": 0,
          "lay": 0
        }
      }
    }
  }
}